Metadata-Version: 2.1
Name: TDY-PKG-saquibquddus
Version: 1.1.1
Summary: its an implimentation of TF-2 , Detectron and yolov5
Home-page: https://github.com/saquibquddus/TDY_PKG
Author: saquibquddus
Author-email: sakibquddus@gmail.com
License: UNKNOWN
Project-URL: Bug Tracker, https://github.com/saquibquddus/TDY_PKG/issues
Platform: UNKNOWN
Classifier: Programming Language :: Python :: 3
Classifier: License :: OSI Approved :: MIT License
Classifier: Operating System :: OS Independent
Requires-Python: >=3.7
License-File: LICENSE
Requires-Dist: seaborn
Requires-Dist: beautifulsoup4 (==4.11.1)
Requires-Dist: filelock (==3.6.0)
Requires-Dist: gdown (==4.4.0)
Requires-Dist: opencv-contrib-python (==4.1.2.30)
Requires-Dist: PySocks (==1.7.1)
Requires-Dist: PyYAML (==6.0)
Requires-Dist: scipy (==1.7.3)
Requires-Dist: soupsieve (==2.3.2)
Requires-Dist: tqdm (==4.64.0)
Requires-Dist: typing-extensions
Requires-Dist: flask
Requires-Dist: flask-cors
Requires-Dist: gunicorn
Requires-Dist: torch
Requires-Dist: torchvision
Requires-Dist: torchaudio
Requires-Dist: pycocotools
Requires-Dist: opencv-python-headless (==4.5.2.52)
Requires-Dist: fvcore
Requires-Dist: omegaconf
Requires-Dist: pandas
Requires-Dist: absl-py
Requires-Dist: apache-beam
Requires-Dist: astunparse
Requires-Dist: avro-python3
Requires-Dist: Bottleneck
Requires-Dist: cached-property
Requires-Dist: cachetools
Requires-Dist: certifi
Requires-Dist: charset-normalizer
Requires-Dist: click
Requires-Dist: cloudpickle
Requires-Dist: colorama
Requires-Dist: crcmod
Requires-Dist: cycler
Requires-Dist: Cython
Requires-Dist: dill
Requires-Dist: docopt
Requires-Dist: fastavro
Requires-Dist: flatbuffers
Requires-Dist: fonttools
Requires-Dist: gast
Requires-Dist: google-auth
Requires-Dist: google-auth-oauthlib
Requires-Dist: google-pasta
Requires-Dist: grpcio
Requires-Dist: h5py
Requires-Dist: hdfs
Requires-Dist: httplib2
Requires-Dist: idna
Requires-Dist: importlib-metadata
Requires-Dist: itsdangerous
Requires-Dist: Jinja2
Requires-Dist: keras-nightly
Requires-Dist: Keras-Preprocessing
Requires-Dist: kiwisolver
Requires-Dist: Markdown
Requires-Dist: MarkupSafe
Requires-Dist: matplotlib
Requires-Dist: mkl-fft
Requires-Dist: mkl-service
Requires-Dist: munkres
Requires-Dist: numpy
Requires-Dist: oauth2client
Requires-Dist: oauthlib
Requires-Dist: opencv-python
Requires-Dist: opt-einsum
Requires-Dist: orjson
Requires-Dist: packaging
Requires-Dist: Pillow
Requires-Dist: proto-plus
Requires-Dist: protobuf
Requires-Dist: pyarrow
Requires-Dist: pyasn1
Requires-Dist: pyasn1-modules
Requires-Dist: pydot
Requires-Dist: pymongo
Requires-Dist: pyparsing
Requires-Dist: python-dateutil
Requires-Dist: pytz
Requires-Dist: requests
Requires-Dist: requests-oauthlib
Requires-Dist: rsa
Requires-Dist: sip
Requires-Dist: six
Requires-Dist: tensorboard (==2.5)
Requires-Dist: tensorflow (==2.5)
Requires-Dist: tensorflow-estimator (==2.5.0)
Requires-Dist: termcolor
Requires-Dist: tf-models-official
Requires-Dist: tf-slim
Requires-Dist: urllib3
Requires-Dist: Werkzeug
Requires-Dist: wincertstore
Requires-Dist: wrapt
Requires-Dist: zipp
